magicsoup-1.0.5.dist-info/METADATA
magicsoup-1.0.5.dist-info/WHEEL
magicsoup-1.0.5.dist-info/license_files/LICENSE
magicsoup/mutations.py
magicsoup/genetics.py
magicsoup/factories.py
magicsoup/containers.py
magicsoup/constants.py
magicsoup/world.py
magicsoup/__init__.py
magicsoup/util.py
magicsoup/kinetics.py
magicsoup/examples/__init__.py
magicsoup/examples/co2_fixing.py
magicsoup/examples/n2_fixing.py
magicsoup/examples/wood_ljungdahl.py
magicsoup/examples/reverse_krebs.py
magicsoup/py.typed
magicsoup/_lib.cpython-310-aarch64-linux-gnu.so
magicsoup-1.0.5.dist-info/RECORD
