Metadata-Version: 2.1
Name: magicsoup
Version: 1.0.5
Classifier: Environment :: Console
Classifier: Environment :: GPU
Classifier: Intended Audience :: Science/Research
Classifier: License :: OSI Approved :: GNU General Public License v3 (GPLv3)
Classifier: Natural Language :: English
Classifier: Operating System :: OS Independent
Classifier: Programming Language :: Python :: 3
Classifier: Topic :: Education
Classifier: Topic :: Games/Entertainment
Classifier: Topic :: Scientific/Engineering
Classifier: Typing :: Typed
Requires-Dist: numpy >=1.24.0, <1.27.0
Requires-Dist: torch >=2.0.0, <2.2.0
License-File: LICENSE
Summary: Simulation for cell metabolic and transduction pathway evolution
Author-email: Marc <schweringmarc01@gmail.com>
Requires-Python: >=3.10
Project-URL: Documentation, https://magic-soup.readthedocs.io/
Project-URL: Homepage, https://github.com/mRcSchwering/magic-soup
Project-URL: Bug Tracker, https://github.com/mRcSchwering/magic-soup/issues
